[
  {
    "id": "54336846-932a-4249-a033-131591102c5e",
    "generated_at": "2026-05-19T10:32:19",
    "anchor_saturday": "2026-06-06",
    "num_weekends": 9,
    "rosters": {
      "morning": [
        "Fernando Luis Euesbio",
        "Boy Jude Renegado",
        "John Carlo Ramiro",
        "Charina Mae Acacio",
        "Felnie Ablanez"
      ],
      "morning_dpt": [
        "Joseph Joaquin Lee"
      ],
      "evening": [
        "Jeno Kyle Recio",
        "Jonas Lipat",
        "Katherine Joy Cocharo"
      ],
      "evening_dpt": [
        "Alvin Kenneth Tria"
      ]
    },
    "assignments": [
      {
        "weekend_index": 1,
        "work_date": "2026-06-06",
        "day_label": "Saturday",
        "time_slot": "6:00 AM - 12:00 PM",
        "setup_type": "On-Shift",
        "shift_name": "Morning",
        "start_time": "06:00",
        "end_time": "12:00",
        "employee": "Fernando Luis Euesbio"
      },
      {
        "weekend_index": 1,
        "work_date": "2026-06-06",
        "day_label": "Saturday",
        "time_slot": "12:00 PM - 6:00 PM",
        "setup_type": "On-call",
        "shift_name": "Morning",
        "start_time": "12:00",
        "end_time": "18:00",
        "employee": "Fernando Luis Euesbio"
      },
      {
        "weekend_index": 1,
        "work_date": "2026-06-06",
        "day_label": "Saturday",
        "time_slot": "7:00 AM - 4:00 PM",
        "setup_type": "On-Shift",
        "shift_name": "Morning DPT",
        "start_time": "07:00",
        "end_time": "16:00",
        "employee": "Joseph Joaquin Lee"
      },
      {
        "weekend_index": 1,
        "work_date": "2026-06-06",
        "day_label": "Saturday",
        "time_slot": "6:00 PM - 12:00 AM",
        "setup_type": "On-Call",
        "shift_name": "Evening",
        "start_time": "18:00",
        "end_time": "00:00",
        "employee": "Jeno Kyle Recio"
      },
      {
        "weekend_index": 1,
        "work_date": "2026-06-06",
        "day_label": "Saturday",
        "time_slot": "12:00 AM - 6:00 AM",
        "setup_type": "On-Shift",
        "shift_name": "Evening",
        "start_time": "00:00",
        "end_time": "06:00",
        "employee": "Jeno Kyle Recio"
      },
      {
        "weekend_index": 1,
        "work_date": "2026-06-06",
        "day_label": "Saturday",
        "time_slot": "10:00 PM - 7:00 AM",
        "setup_type": "On-Shift",
        "shift_name": "Evening DPT",
        "start_time": "22:00",
        "end_time": "07:00",
        "employee": "Alvin Kenneth Tria"
      },
      {
        "weekend_index": 1,
        "work_date": "2026-06-07",
        "day_label": "Sunday",
        "time_slot": "6:00 AM - 12:00 PM",
        "setup_type": "On-Shift",
        "shift_name": "Morning",
        "start_time": "06:00",
        "end_time": "12:00",
        "employee": "Boy Jude Renegado"
      },
      {
        "weekend_index": 1,
        "work_date": "2026-06-07",
        "day_label": "Sunday",
        "time_slot": "12:00 PM - 6:00 PM",
        "setup_type": "On-call",
        "shift_name": "Morning",
        "start_time": "12:00",
        "end_time": "18:00",
        "employee": "Boy Jude Renegado"
      },
      {
        "weekend_index": 1,
        "work_date": "2026-06-07",
        "day_label": "Sunday",
        "time_slot": "7:00 AM - 4:00 PM",
        "setup_type": "On-Shift",
        "shift_name": "Morning DPT",
        "start_time": "07:00",
        "end_time": "16:00",
        "employee": "Joseph Joaquin Lee"
      },
      {
        "weekend_index": 1,
        "work_date": "2026-06-07",
        "day_label": "Sunday",
        "time_slot": "6:00 PM - 12:00 AM",
        "setup_type": "On-Call",
        "shift_name": "Evening",
        "start_time": "18:00",
        "end_time": "00:00",
        "employee": "Jonas Lipat"
      },
      {
        "weekend_index": 1,
        "work_date": "2026-06-07",
        "day_label": "Sunday",
        "time_slot": "12:00 AM - 6:00 AM",
        "setup_type": "On-Shift",
        "shift_name": "Evening",
        "start_time": "00:00",
        "end_time": "06:00",
        "employee": "Jonas Lipat"
      },
      {
        "weekend_index": 1,
        "work_date": "2026-06-07",
        "day_label": "Sunday",
        "time_slot": "10:00 PM - 7:00 AM",
        "setup_type": "On-Shift",
        "shift_name": "Evening DPT",
        "start_time": "22:00",
        "end_time": "07:00",
        "employee": "Alvin Kenneth Tria"
      },
      {
        "weekend_index": 2,
        "work_date": "2026-06-13",
        "day_label": "Saturday",
        "time_slot": "6:00 AM - 12:00 PM",
        "setup_type": "On-Shift",
        "shift_name": "Morning",
        "start_time": "06:00",
        "end_time": "12:00",
        "employee": "John Carlo Ramiro"
      },
      {
        "weekend_index": 2,
        "work_date": "2026-06-13",
        "day_label": "Saturday",
        "time_slot": "12:00 PM - 6:00 PM",
        "setup_type": "On-call",
        "shift_name": "Morning",
        "start_time": "12:00",
        "end_time": "18:00",
        "employee": "John Carlo Ramiro"
      },
      {
        "weekend_index": 2,
        "work_date": "2026-06-13",
        "day_label": "Saturday",
        "time_slot": "7:00 AM - 4:00 PM",
        "setup_type": "On-Shift",
        "shift_name": "Morning DPT",
        "start_time": "07:00",
        "end_time": "16:00",
        "employee": "Joseph Joaquin Lee"
      },
      {
        "weekend_index": 2,
        "work_date": "2026-06-13",
        "day_label": "Saturday",
        "time_slot": "6:00 PM - 12:00 AM",
        "setup_type": "On-Call",
        "shift_name": "Evening",
        "start_time": "18:00",
        "end_time": "00:00",
        "employee": "Katherine Joy Cocharo"
      },
      {
        "weekend_index": 2,
        "work_date": "2026-06-13",
        "day_label": "Saturday",
        "time_slot": "12:00 AM - 6:00 AM",
        "setup_type": "On-Shift",
        "shift_name": "Evening",
        "start_time": "00:00",
        "end_time": "06:00",
        "employee": "Katherine Joy Cocharo"
      },
      {
        "weekend_index": 2,
        "work_date": "2026-06-13",
        "day_label": "Saturday",
        "time_slot": "10:00 PM - 7:00 AM",
        "setup_type": "On-Shift",
        "shift_name": "Evening DPT",
        "start_time": "22:00",
        "end_time": "07:00",
        "employee": "Alvin Kenneth Tria"
      },
      {
        "weekend_index": 2,
        "work_date": "2026-06-14",
        "day_label": "Sunday",
        "time_slot": "6:00 AM - 12:00 PM",
        "setup_type": "On-Shift",
        "shift_name": "Morning",
        "start_time": "06:00",
        "end_time": "12:00",
        "employee": "Charina Mae Acacio"
      },
      {
        "weekend_index": 2,
        "work_date": "2026-06-14",
        "day_label": "Sunday",
        "time_slot": "12:00 PM - 6:00 PM",
        "setup_type": "On-call",
        "shift_name": "Morning",
        "start_time": "12:00",
        "end_time": "18:00",
        "employee": "Charina Mae Acacio"
      },
      {
        "weekend_index": 2,
        "work_date": "2026-06-14",
        "day_label": "Sunday",
        "time_slot": "7:00 AM - 4:00 PM",
        "setup_type": "On-Shift",
        "shift_name": "Morning DPT",
        "start_time": "07:00",
        "end_time": "16:00",
        "employee": "Joseph Joaquin Lee"
      },
      {
        "weekend_index": 2,
        "work_date": "2026-06-14",
        "day_label": "Sunday",
        "time_slot": "6:00 PM - 12:00 AM",
        "setup_type": "On-Call",
        "shift_name": "Evening",
        "start_time": "18:00",
        "end_time": "00:00",
        "employee": "Jeno Kyle Recio"
      },
      {
        "weekend_index": 2,
        "work_date": "2026-06-14",
        "day_label": "Sunday",
        "time_slot": "12:00 AM - 6:00 AM",
        "setup_type": "On-Shift",
        "shift_name": "Evening",
        "start_time": "00:00",
        "end_time": "06:00",
        "employee": "Jeno Kyle Recio"
      },
      {
        "weekend_index": 2,
        "work_date": "2026-06-14",
        "day_label": "Sunday",
        "time_slot": "10:00 PM - 7:00 AM",
        "setup_type": "On-Shift",
        "shift_name": "Evening DPT",
        "start_time": "22:00",
        "end_time": "07:00",
        "employee": "Alvin Kenneth Tria"
      },
      {
        "weekend_index": 3,
        "work_date": "2026-06-20",
        "day_label": "Saturday",
        "time_slot": "6:00 AM - 12:00 PM",
        "setup_type": "On-Shift",
        "shift_name": "Morning",
        "start_time": "06:00",
        "end_time": "12:00",
        "employee": "Felnie Ablanez"
      },
      {
        "weekend_index": 3,
        "work_date": "2026-06-20",
        "day_label": "Saturday",
        "time_slot": "12:00 PM - 6:00 PM",
        "setup_type": "On-call",
        "shift_name": "Morning",
        "start_time": "12:00",
        "end_time": "18:00",
        "employee": "Felnie Ablanez"
      },
      {
        "weekend_index": 3,
        "work_date": "2026-06-20",
        "day_label": "Saturday",
        "time_slot": "7:00 AM - 4:00 PM",
        "setup_type": "On-Shift",
        "shift_name": "Morning DPT",
        "start_time": "07:00",
        "end_time": "16:00",
        "employee": "Joseph Joaquin Lee"
      },
      {
        "weekend_index": 3,
        "work_date": "2026-06-20",
        "day_label": "Saturday",
        "time_slot": "6:00 PM - 12:00 AM",
        "setup_type": "On-Call",
        "shift_name": "Evening",
        "start_time": "18:00",
        "end_time": "00:00",
        "employee": "Jonas Lipat"
      },
      {
        "weekend_index": 3,
        "work_date": "2026-06-20",
        "day_label": "Saturday",
        "time_slot": "12:00 AM - 6:00 AM",
        "setup_type": "On-Shift",
        "shift_name": "Evening",
        "start_time": "00:00",
        "end_time": "06:00",
        "employee": "Jonas Lipat"
      },
      {
        "weekend_index": 3,
        "work_date": "2026-06-20",
        "day_label": "Saturday",
        "time_slot": "10:00 PM - 7:00 AM",
        "setup_type": "On-Shift",
        "shift_name": "Evening DPT",
        "start_time": "22:00",
        "end_time": "07:00",
        "employee": "Alvin Kenneth Tria"
      },
      {
        "weekend_index": 3,
        "work_date": "2026-06-21",
        "day_label": "Sunday",
        "time_slot": "6:00 AM - 12:00 PM",
        "setup_type": "On-Shift",
        "shift_name": "Morning",
        "start_time": "06:00",
        "end_time": "12:00",
        "employee": "Fernando Luis Euesbio"
      },
      {
        "weekend_index": 3,
        "work_date": "2026-06-21",
        "day_label": "Sunday",
        "time_slot": "12:00 PM - 6:00 PM",
        "setup_type": "On-call",
        "shift_name": "Morning",
        "start_time": "12:00",
        "end_time": "18:00",
        "employee": "Fernando Luis Euesbio"
      },
      {
        "weekend_index": 3,
        "work_date": "2026-06-21",
        "day_label": "Sunday",
        "time_slot": "7:00 AM - 4:00 PM",
        "setup_type": "On-Shift",
        "shift_name": "Morning DPT",
        "start_time": "07:00",
        "end_time": "16:00",
        "employee": "Joseph Joaquin Lee"
      },
      {
        "weekend_index": 3,
        "work_date": "2026-06-21",
        "day_label": "Sunday",
        "time_slot": "6:00 PM - 12:00 AM",
        "setup_type": "On-Call",
        "shift_name": "Evening",
        "start_time": "18:00",
        "end_time": "00:00",
        "employee": "Katherine Joy Cocharo"
      },
      {
        "weekend_index": 3,
        "work_date": "2026-06-21",
        "day_label": "Sunday",
        "time_slot": "12:00 AM - 6:00 AM",
        "setup_type": "On-Shift",
        "shift_name": "Evening",
        "start_time": "00:00",
        "end_time": "06:00",
        "employee": "Katherine Joy Cocharo"
      },
      {
        "weekend_index": 3,
        "work_date": "2026-06-21",
        "day_label": "Sunday",
        "time_slot": "10:00 PM - 7:00 AM",
        "setup_type": "On-Shift",
        "shift_name": "Evening DPT",
        "start_time": "22:00",
        "end_time": "07:00",
        "employee": "Alvin Kenneth Tria"
      },
      {
        "weekend_index": 4,
        "work_date": "2026-06-27",
        "day_label": "Saturday",
        "time_slot": "6:00 AM - 12:00 PM",
        "setup_type": "On-Shift",
        "shift_name": "Morning",
        "start_time": "06:00",
        "end_time": "12:00",
        "employee": "Boy Jude Renegado"
      },
      {
        "weekend_index": 4,
        "work_date": "2026-06-27",
        "day_label": "Saturday",
        "time_slot": "12:00 PM - 6:00 PM",
        "setup_type": "On-call",
        "shift_name": "Morning",
        "start_time": "12:00",
        "end_time": "18:00",
        "employee": "Boy Jude Renegado"
      },
      {
        "weekend_index": 4,
        "work_date": "2026-06-27",
        "day_label": "Saturday",
        "time_slot": "7:00 AM - 4:00 PM",
        "setup_type": "On-Shift",
        "shift_name": "Morning DPT",
        "start_time": "07:00",
        "end_time": "16:00",
        "employee": "Joseph Joaquin Lee"
      },
      {
        "weekend_index": 4,
        "work_date": "2026-06-27",
        "day_label": "Saturday",
        "time_slot": "6:00 PM - 12:00 AM",
        "setup_type": "On-Call",
        "shift_name": "Evening",
        "start_time": "18:00",
        "end_time": "00:00",
        "employee": "Jeno Kyle Recio"
      },
      {
        "weekend_index": 4,
        "work_date": "2026-06-27",
        "day_label": "Saturday",
        "time_slot": "12:00 AM - 6:00 AM",
        "setup_type": "On-Shift",
        "shift_name": "Evening",
        "start_time": "00:00",
        "end_time": "06:00",
        "employee": "Jeno Kyle Recio"
      },
      {
        "weekend_index": 4,
        "work_date": "2026-06-27",
        "day_label": "Saturday",
        "time_slot": "10:00 PM - 7:00 AM",
        "setup_type": "On-Shift",
        "shift_name": "Evening DPT",
        "start_time": "22:00",
        "end_time": "07:00",
        "employee": "Alvin Kenneth Tria"
      },
      {
        "weekend_index": 4,
        "work_date": "2026-06-28",
        "day_label": "Sunday",
        "time_slot": "6:00 AM - 12:00 PM",
        "setup_type": "On-Shift",
        "shift_name": "Morning",
        "start_time": "06:00",
        "end_time": "12:00",
        "employee": "John Carlo Ramiro"
      },
      {
        "weekend_index": 4,
        "work_date": "2026-06-28",
        "day_label": "Sunday",
        "time_slot": "12:00 PM - 6:00 PM",
        "setup_type": "On-call",
        "shift_name": "Morning",
        "start_time": "12:00",
        "end_time": "18:00",
        "employee": "John Carlo Ramiro"
      },
      {
        "weekend_index": 4,
        "work_date": "2026-06-28",
        "day_label": "Sunday",
        "time_slot": "7:00 AM - 4:00 PM",
        "setup_type": "On-Shift",
        "shift_name": "Morning DPT",
        "start_time": "07:00",
        "end_time": "16:00",
        "employee": "Joseph Joaquin Lee"
      },
      {
        "weekend_index": 4,
        "work_date": "2026-06-28",
        "day_label": "Sunday",
        "time_slot": "6:00 PM - 12:00 AM",
        "setup_type": "On-Call",
        "shift_name": "Evening",
        "start_time": "18:00",
        "end_time": "00:00",
        "employee": "Jonas Lipat"
      },
      {
        "weekend_index": 4,
        "work_date": "2026-06-28",
        "day_label": "Sunday",
        "time_slot": "12:00 AM - 6:00 AM",
        "setup_type": "On-Shift",
        "shift_name": "Evening",
        "start_time": "00:00",
        "end_time": "06:00",
        "employee": "Jonas Lipat"
      },
      {
        "weekend_index": 4,
        "work_date": "2026-06-28",
        "day_label": "Sunday",
        "time_slot": "10:00 PM - 7:00 AM",
        "setup_type": "On-Shift",
        "shift_name": "Evening DPT",
        "start_time": "22:00",
        "end_time": "07:00",
        "employee": "Alvin Kenneth Tria"
      },
      {
        "weekend_index": 5,
        "work_date": "2026-07-04",
        "day_label": "Saturday",
        "time_slot": "6:00 AM - 12:00 PM",
        "setup_type": "On-Shift",
        "shift_name": "Morning",
        "start_time": "06:00",
        "end_time": "12:00",
        "employee": "Charina Mae Acacio"
      },
      {
        "weekend_index": 5,
        "work_date": "2026-07-04",
        "day_label": "Saturday",
        "time_slot": "12:00 PM - 6:00 PM",
        "setup_type": "On-call",
        "shift_name": "Morning",
        "start_time": "12:00",
        "end_time": "18:00",
        "employee": "Charina Mae Acacio"
      },
      {
        "weekend_index": 5,
        "work_date": "2026-07-04",
        "day_label": "Saturday",
        "time_slot": "7:00 AM - 4:00 PM",
        "setup_type": "On-Shift",
        "shift_name": "Morning DPT",
        "start_time": "07:00",
        "end_time": "16:00",
        "employee": "Joseph Joaquin Lee"
      },
      {
        "weekend_index": 5,
        "work_date": "2026-07-04",
        "day_label": "Saturday",
        "time_slot": "6:00 PM - 12:00 AM",
        "setup_type": "On-Call",
        "shift_name": "Evening",
        "start_time": "18:00",
        "end_time": "00:00",
        "employee": "Katherine Joy Cocharo"
      },
      {
        "weekend_index": 5,
        "work_date": "2026-07-04",
        "day_label": "Saturday",
        "time_slot": "12:00 AM - 6:00 AM",
        "setup_type": "On-Shift",
        "shift_name": "Evening",
        "start_time": "00:00",
        "end_time": "06:00",
        "employee": "Katherine Joy Cocharo"
      },
      {
        "weekend_index": 5,
        "work_date": "2026-07-04",
        "day_label": "Saturday",
        "time_slot": "10:00 PM - 7:00 AM",
        "setup_type": "On-Shift",
        "shift_name": "Evening DPT",
        "start_time": "22:00",
        "end_time": "07:00",
        "employee": "Alvin Kenneth Tria"
      },
      {
        "weekend_index": 5,
        "work_date": "2026-07-05",
        "day_label": "Sunday",
        "time_slot": "6:00 AM - 12:00 PM",
        "setup_type": "On-Shift",
        "shift_name": "Morning",
        "start_time": "06:00",
        "end_time": "12:00",
        "employee": "Felnie Ablanez"
      },
      {
        "weekend_index": 5,
        "work_date": "2026-07-05",
        "day_label": "Sunday",
        "time_slot": "12:00 PM - 6:00 PM",
        "setup_type": "On-call",
        "shift_name": "Morning",
        "start_time": "12:00",
        "end_time": "18:00",
        "employee": "Felnie Ablanez"
      },
      {
        "weekend_index": 5,
        "work_date": "2026-07-05",
        "day_label": "Sunday",
        "time_slot": "7:00 AM - 4:00 PM",
        "setup_type": "On-Shift",
        "shift_name": "Morning DPT",
        "start_time": "07:00",
        "end_time": "16:00",
        "employee": "Joseph Joaquin Lee"
      },
      {
        "weekend_index": 5,
        "work_date": "2026-07-05",
        "day_label": "Sunday",
        "time_slot": "6:00 PM - 12:00 AM",
        "setup_type": "On-Call",
        "shift_name": "Evening",
        "start_time": "18:00",
        "end_time": "00:00",
        "employee": "Jeno Kyle Recio"
      },
      {
        "weekend_index": 5,
        "work_date": "2026-07-05",
        "day_label": "Sunday",
        "time_slot": "12:00 AM - 6:00 AM",
        "setup_type": "On-Shift",
        "shift_name": "Evening",
        "start_time": "00:00",
        "end_time": "06:00",
        "employee": "Jeno Kyle Recio"
      },
      {
        "weekend_index": 5,
        "work_date": "2026-07-05",
        "day_label": "Sunday",
        "time_slot": "10:00 PM - 7:00 AM",
        "setup_type": "On-Shift",
        "shift_name": "Evening DPT",
        "start_time": "22:00",
        "end_time": "07:00",
        "employee": "Alvin Kenneth Tria"
      },
      {
        "weekend_index": 6,
        "work_date": "2026-07-11",
        "day_label": "Saturday",
        "time_slot": "6:00 AM - 12:00 PM",
        "setup_type": "On-Shift",
        "shift_name": "Morning",
        "start_time": "06:00",
        "end_time": "12:00",
        "employee": "Fernando Luis Euesbio"
      },
      {
        "weekend_index": 6,
        "work_date": "2026-07-11",
        "day_label": "Saturday",
        "time_slot": "12:00 PM - 6:00 PM",
        "setup_type": "On-call",
        "shift_name": "Morning",
        "start_time": "12:00",
        "end_time": "18:00",
        "employee": "Fernando Luis Euesbio"
      },
      {
        "weekend_index": 6,
        "work_date": "2026-07-11",
        "day_label": "Saturday",
        "time_slot": "7:00 AM - 4:00 PM",
        "setup_type": "On-Shift",
        "shift_name": "Morning DPT",
        "start_time": "07:00",
        "end_time": "16:00",
        "employee": "Joseph Joaquin Lee"
      },
      {
        "weekend_index": 6,
        "work_date": "2026-07-11",
        "day_label": "Saturday",
        "time_slot": "6:00 PM - 12:00 AM",
        "setup_type": "On-Call",
        "shift_name": "Evening",
        "start_time": "18:00",
        "end_time": "00:00",
        "employee": "Jonas Lipat"
      },
      {
        "weekend_index": 6,
        "work_date": "2026-07-11",
        "day_label": "Saturday",
        "time_slot": "12:00 AM - 6:00 AM",
        "setup_type": "On-Shift",
        "shift_name": "Evening",
        "start_time": "00:00",
        "end_time": "06:00",
        "employee": "Jonas Lipat"
      },
      {
        "weekend_index": 6,
        "work_date": "2026-07-11",
        "day_label": "Saturday",
        "time_slot": "10:00 PM - 7:00 AM",
        "setup_type": "On-Shift",
        "shift_name": "Evening DPT",
        "start_time": "22:00",
        "end_time": "07:00",
        "employee": "Alvin Kenneth Tria"
      },
      {
        "weekend_index": 6,
        "work_date": "2026-07-12",
        "day_label": "Sunday",
        "time_slot": "6:00 AM - 12:00 PM",
        "setup_type": "On-Shift",
        "shift_name": "Morning",
        "start_time": "06:00",
        "end_time": "12:00",
        "employee": "Boy Jude Renegado"
      },
      {
        "weekend_index": 6,
        "work_date": "2026-07-12",
        "day_label": "Sunday",
        "time_slot": "12:00 PM - 6:00 PM",
        "setup_type": "On-call",
        "shift_name": "Morning",
        "start_time": "12:00",
        "end_time": "18:00",
        "employee": "Boy Jude Renegado"
      },
      {
        "weekend_index": 6,
        "work_date": "2026-07-12",
        "day_label": "Sunday",
        "time_slot": "7:00 AM - 4:00 PM",
        "setup_type": "On-Shift",
        "shift_name": "Morning DPT",
        "start_time": "07:00",
        "end_time": "16:00",
        "employee": "Joseph Joaquin Lee"
      },
      {
        "weekend_index": 6,
        "work_date": "2026-07-12",
        "day_label": "Sunday",
        "time_slot": "6:00 PM - 12:00 AM",
        "setup_type": "On-Call",
        "shift_name": "Evening",
        "start_time": "18:00",
        "end_time": "00:00",
        "employee": "Katherine Joy Cocharo"
      },
      {
        "weekend_index": 6,
        "work_date": "2026-07-12",
        "day_label": "Sunday",
        "time_slot": "12:00 AM - 6:00 AM",
        "setup_type": "On-Shift",
        "shift_name": "Evening",
        "start_time": "00:00",
        "end_time": "06:00",
        "employee": "Katherine Joy Cocharo"
      },
      {
        "weekend_index": 6,
        "work_date": "2026-07-12",
        "day_label": "Sunday",
        "time_slot": "10:00 PM - 7:00 AM",
        "setup_type": "On-Shift",
        "shift_name": "Evening DPT",
        "start_time": "22:00",
        "end_time": "07:00",
        "employee": "Alvin Kenneth Tria"
      },
      {
        "weekend_index": 7,
        "work_date": "2026-07-18",
        "day_label": "Saturday",
        "time_slot": "6:00 AM - 12:00 PM",
        "setup_type": "On-Shift",
        "shift_name": "Morning",
        "start_time": "06:00",
        "end_time": "12:00",
        "employee": "John Carlo Ramiro"
      },
      {
        "weekend_index": 7,
        "work_date": "2026-07-18",
        "day_label": "Saturday",
        "time_slot": "12:00 PM - 6:00 PM",
        "setup_type": "On-call",
        "shift_name": "Morning",
        "start_time": "12:00",
        "end_time": "18:00",
        "employee": "John Carlo Ramiro"
      },
      {
        "weekend_index": 7,
        "work_date": "2026-07-18",
        "day_label": "Saturday",
        "time_slot": "7:00 AM - 4:00 PM",
        "setup_type": "On-Shift",
        "shift_name": "Morning DPT",
        "start_time": "07:00",
        "end_time": "16:00",
        "employee": "Joseph Joaquin Lee"
      },
      {
        "weekend_index": 7,
        "work_date": "2026-07-18",
        "day_label": "Saturday",
        "time_slot": "6:00 PM - 12:00 AM",
        "setup_type": "On-Call",
        "shift_name": "Evening",
        "start_time": "18:00",
        "end_time": "00:00",
        "employee": "Jeno Kyle Recio"
      },
      {
        "weekend_index": 7,
        "work_date": "2026-07-18",
        "day_label": "Saturday",
        "time_slot": "12:00 AM - 6:00 AM",
        "setup_type": "On-Shift",
        "shift_name": "Evening",
        "start_time": "00:00",
        "end_time": "06:00",
        "employee": "Jeno Kyle Recio"
      },
      {
        "weekend_index": 7,
        "work_date": "2026-07-18",
        "day_label": "Saturday",
        "time_slot": "10:00 PM - 7:00 AM",
        "setup_type": "On-Shift",
        "shift_name": "Evening DPT",
        "start_time": "22:00",
        "end_time": "07:00",
        "employee": "Alvin Kenneth Tria"
      },
      {
        "weekend_index": 7,
        "work_date": "2026-07-19",
        "day_label": "Sunday",
        "time_slot": "6:00 AM - 12:00 PM",
        "setup_type": "On-Shift",
        "shift_name": "Morning",
        "start_time": "06:00",
        "end_time": "12:00",
        "employee": "Charina Mae Acacio"
      },
      {
        "weekend_index": 7,
        "work_date": "2026-07-19",
        "day_label": "Sunday",
        "time_slot": "12:00 PM - 6:00 PM",
        "setup_type": "On-call",
        "shift_name": "Morning",
        "start_time": "12:00",
        "end_time": "18:00",
        "employee": "Charina Mae Acacio"
      },
      {
        "weekend_index": 7,
        "work_date": "2026-07-19",
        "day_label": "Sunday",
        "time_slot": "7:00 AM - 4:00 PM",
        "setup_type": "On-Shift",
        "shift_name": "Morning DPT",
        "start_time": "07:00",
        "end_time": "16:00",
        "employee": "Joseph Joaquin Lee"
      },
      {
        "weekend_index": 7,
        "work_date": "2026-07-19",
        "day_label": "Sunday",
        "time_slot": "6:00 PM - 12:00 AM",
        "setup_type": "On-Call",
        "shift_name": "Evening",
        "start_time": "18:00",
        "end_time": "00:00",
        "employee": "Jonas Lipat"
      },
      {
        "weekend_index": 7,
        "work_date": "2026-07-19",
        "day_label": "Sunday",
        "time_slot": "12:00 AM - 6:00 AM",
        "setup_type": "On-Shift",
        "shift_name": "Evening",
        "start_time": "00:00",
        "end_time": "06:00",
        "employee": "Jonas Lipat"
      },
      {
        "weekend_index": 7,
        "work_date": "2026-07-19",
        "day_label": "Sunday",
        "time_slot": "10:00 PM - 7:00 AM",
        "setup_type": "On-Shift",
        "shift_name": "Evening DPT",
        "start_time": "22:00",
        "end_time": "07:00",
        "employee": "Alvin Kenneth Tria"
      },
      {
        "weekend_index": 8,
        "work_date": "2026-07-25",
        "day_label": "Saturday",
        "time_slot": "6:00 AM - 12:00 PM",
        "setup_type": "On-Shift",
        "shift_name": "Morning",
        "start_time": "06:00",
        "end_time": "12:00",
        "employee": "Felnie Ablanez"
      },
      {
        "weekend_index": 8,
        "work_date": "2026-07-25",
        "day_label": "Saturday",
        "time_slot": "12:00 PM - 6:00 PM",
        "setup_type": "On-call",
        "shift_name": "Morning",
        "start_time": "12:00",
        "end_time": "18:00",
        "employee": "Felnie Ablanez"
      },
      {
        "weekend_index": 8,
        "work_date": "2026-07-25",
        "day_label": "Saturday",
        "time_slot": "7:00 AM - 4:00 PM",
        "setup_type": "On-Shift",
        "shift_name": "Morning DPT",
        "start_time": "07:00",
        "end_time": "16:00",
        "employee": "Joseph Joaquin Lee"
      },
      {
        "weekend_index": 8,
        "work_date": "2026-07-25",
        "day_label": "Saturday",
        "time_slot": "6:00 PM - 12:00 AM",
        "setup_type": "On-Call",
        "shift_name": "Evening",
        "start_time": "18:00",
        "end_time": "00:00",
        "employee": "Katherine Joy Cocharo"
      },
      {
        "weekend_index": 8,
        "work_date": "2026-07-25",
        "day_label": "Saturday",
        "time_slot": "12:00 AM - 6:00 AM",
        "setup_type": "On-Shift",
        "shift_name": "Evening",
        "start_time": "00:00",
        "end_time": "06:00",
        "employee": "Katherine Joy Cocharo"
      },
      {
        "weekend_index": 8,
        "work_date": "2026-07-25",
        "day_label": "Saturday",
        "time_slot": "10:00 PM - 7:00 AM",
        "setup_type": "On-Shift",
        "shift_name": "Evening DPT",
        "start_time": "22:00",
        "end_time": "07:00",
        "employee": "Alvin Kenneth Tria"
      },
      {
        "weekend_index": 8,
        "work_date": "2026-07-26",
        "day_label": "Sunday",
        "time_slot": "6:00 AM - 12:00 PM",
        "setup_type": "On-Shift",
        "shift_name": "Morning",
        "start_time": "06:00",
        "end_time": "12:00",
        "employee": "Fernando Luis Euesbio"
      },
      {
        "weekend_index": 8,
        "work_date": "2026-07-26",
        "day_label": "Sunday",
        "time_slot": "12:00 PM - 6:00 PM",
        "setup_type": "On-call",
        "shift_name": "Morning",
        "start_time": "12:00",
        "end_time": "18:00",
        "employee": "Fernando Luis Euesbio"
      },
      {
        "weekend_index": 8,
        "work_date": "2026-07-26",
        "day_label": "Sunday",
        "time_slot": "7:00 AM - 4:00 PM",
        "setup_type": "On-Shift",
        "shift_name": "Morning DPT",
        "start_time": "07:00",
        "end_time": "16:00",
        "employee": "Joseph Joaquin Lee"
      },
      {
        "weekend_index": 8,
        "work_date": "2026-07-26",
        "day_label": "Sunday",
        "time_slot": "6:00 PM - 12:00 AM",
        "setup_type": "On-Call",
        "shift_name": "Evening",
        "start_time": "18:00",
        "end_time": "00:00",
        "employee": "Jeno Kyle Recio"
      },
      {
        "weekend_index": 8,
        "work_date": "2026-07-26",
        "day_label": "Sunday",
        "time_slot": "12:00 AM - 6:00 AM",
        "setup_type": "On-Shift",
        "shift_name": "Evening",
        "start_time": "00:00",
        "end_time": "06:00",
        "employee": "Jeno Kyle Recio"
      },
      {
        "weekend_index": 8,
        "work_date": "2026-07-26",
        "day_label": "Sunday",
        "time_slot": "10:00 PM - 7:00 AM",
        "setup_type": "On-Shift",
        "shift_name": "Evening DPT",
        "start_time": "22:00",
        "end_time": "07:00",
        "employee": "Alvin Kenneth Tria"
      },
      {
        "weekend_index": 9,
        "work_date": "2026-08-01",
        "day_label": "Saturday",
        "time_slot": "6:00 AM - 12:00 PM",
        "setup_type": "On-Shift",
        "shift_name": "Morning",
        "start_time": "06:00",
        "end_time": "12:00",
        "employee": "Boy Jude Renegado"
      },
      {
        "weekend_index": 9,
        "work_date": "2026-08-01",
        "day_label": "Saturday",
        "time_slot": "12:00 PM - 6:00 PM",
        "setup_type": "On-call",
        "shift_name": "Morning",
        "start_time": "12:00",
        "end_time": "18:00",
        "employee": "Boy Jude Renegado"
      },
      {
        "weekend_index": 9,
        "work_date": "2026-08-01",
        "day_label": "Saturday",
        "time_slot": "7:00 AM - 4:00 PM",
        "setup_type": "On-Shift",
        "shift_name": "Morning DPT",
        "start_time": "07:00",
        "end_time": "16:00",
        "employee": "Joseph Joaquin Lee"
      },
      {
        "weekend_index": 9,
        "work_date": "2026-08-01",
        "day_label": "Saturday",
        "time_slot": "6:00 PM - 12:00 AM",
        "setup_type": "On-Call",
        "shift_name": "Evening",
        "start_time": "18:00",
        "end_time": "00:00",
        "employee": "Jonas Lipat"
      },
      {
        "weekend_index": 9,
        "work_date": "2026-08-01",
        "day_label": "Saturday",
        "time_slot": "12:00 AM - 6:00 AM",
        "setup_type": "On-Shift",
        "shift_name": "Evening",
        "start_time": "00:00",
        "end_time": "06:00",
        "employee": "Jonas Lipat"
      },
      {
        "weekend_index": 9,
        "work_date": "2026-08-01",
        "day_label": "Saturday",
        "time_slot": "10:00 PM - 7:00 AM",
        "setup_type": "On-Shift",
        "shift_name": "Evening DPT",
        "start_time": "22:00",
        "end_time": "07:00",
        "employee": "Alvin Kenneth Tria"
      },
      {
        "weekend_index": 9,
        "work_date": "2026-08-02",
        "day_label": "Sunday",
        "time_slot": "6:00 AM - 12:00 PM",
        "setup_type": "On-Shift",
        "shift_name": "Morning",
        "start_time": "06:00",
        "end_time": "12:00",
        "employee": "John Carlo Ramiro"
      },
      {
        "weekend_index": 9,
        "work_date": "2026-08-02",
        "day_label": "Sunday",
        "time_slot": "12:00 PM - 6:00 PM",
        "setup_type": "On-call",
        "shift_name": "Morning",
        "start_time": "12:00",
        "end_time": "18:00",
        "employee": "John Carlo Ramiro"
      },
      {
        "weekend_index": 9,
        "work_date": "2026-08-02",
        "day_label": "Sunday",
        "time_slot": "7:00 AM - 4:00 PM",
        "setup_type": "On-Shift",
        "shift_name": "Morning DPT",
        "start_time": "07:00",
        "end_time": "16:00",
        "employee": "Joseph Joaquin Lee"
      },
      {
        "weekend_index": 9,
        "work_date": "2026-08-02",
        "day_label": "Sunday",
        "time_slot": "6:00 PM - 12:00 AM",
        "setup_type": "On-Call",
        "shift_name": "Evening",
        "start_time": "18:00",
        "end_time": "00:00",
        "employee": "Katherine Joy Cocharo"
      },
      {
        "weekend_index": 9,
        "work_date": "2026-08-02",
        "day_label": "Sunday",
        "time_slot": "12:00 AM - 6:00 AM",
        "setup_type": "On-Shift",
        "shift_name": "Evening",
        "start_time": "00:00",
        "end_time": "06:00",
        "employee": "Katherine Joy Cocharo"
      },
      {
        "weekend_index": 9,
        "work_date": "2026-08-02",
        "day_label": "Sunday",
        "time_slot": "10:00 PM - 7:00 AM",
        "setup_type": "On-Shift",
        "shift_name": "Evening DPT",
        "start_time": "22:00",
        "end_time": "07:00",
        "employee": "Alvin Kenneth Tria"
      }
    ]
  }
]